{
    "NSFW": "UNLIKELY",
    "similarity": 0.3933151662349701,
    "LICENSE": "?",
    "caption": "I Wear Purple For My Wife Purple Ribbon Key Chain",
    "url": "http://rlv.zcache.co.uk/i_wear_purple_for_my_wife_purple_ribbon_key_ring-r0f8cfac0296a4dca8027e46ac4b63007_x7j3z_8byvr_324.jpg",
    "key": "033367630",
    "status": "success",
    "error_message": null,
    "width": 324,
    "height": 324,
    "exif": "{\"Image ExifOffset\": \"22\"}",
    "original_width": 324,
    "original_height": 324
}